<?xml version="1.0" encoding="utf-8" ?>
<Silk>

  <Prefixes>
    <Prefix id="rdfs" namespace="http://www.w3.org/2000/01/rdf-schema#" />
    <Prefix id="dbpedia" namespace="http://dbpedia.org/ontology/" />
    <Prefix id="dbpedia-owl" namespace="http://dbpedia.org/ontology/" />
    <Prefix id="umbel-sc" namespace="http://umbel.org/umbel/sc/" />    	    		
    <Prefix id="linkedgeodata" namespace="http://linkedgeodata.org/triplify/" />
    <Prefix id="lgdp" namespace="http://linkedgeodata.org/property/" />
    <Prefix id="lgdo" namespace="http://linkedgeodata.org/ontology/" />
    <Prefix id="owl" namespace="http://www.w3.org/2002/07/owl#" />
    <Prefix id="geo" namespace="http://www.w3.org/2003/01/geo/wgs84_pos#" />
    <Prefix id="foaf" namespace="http://xmlns.com/foaf/0.1/" />    
    <Prefix id="wgs84" namespace="http://www.w3.org/2003/01/geo/wgs84_pos#" />
  </Prefixes>

 <DataSources>
    <DataSource id="dbpedia" type="sparqlEndpoint">
      <Param value="http://160.45.137.69:3030/dbpedia/query" name="endpointURI"></Param>
	  <!-- <Param value="http://dbpedia.org/sparql" name="endpointURI"></Param>  -->
      <!-- <Param value="http://dbpedia.org/" name="graph"></Param> --><Param name="retryCount" value="1000" />
      <Param name="retryCount" value="100" />
      <Param name="retryPause" value="10000" />            
    </DataSource>
    <DataSource id="linkedgeodata" type="sparqlEndpoint">
      <Param name="endpointURI" value="http://linkedgeodata.org/sparql/" />
      <Param name="graph" value="http://linkedgeodata.org" />
      <Param name="retryCount" value="100" />
      <Param name="retryPause" value="10000" />      
    </DataSource>
  </DataSources>

 <!--<Blocking blocks="100"/>-->

  <Interlinks>
    <Interlink id="stadium">
      <LinkType>owl:sameAs</LinkType>

      <SourceDataset dataSource="dbpedia" var="a">
        <RestrictTo>
          ?a a dbpedia-owl:Stadium.  ?a wgs84:lat ?lat. ?a wgs84:long ?long.
        </RestrictTo>
      </SourceDataset>

      <TargetDataset dataSource="linkedgeodata" var="b">
        <RestrictTo>
          ?b a lgdo:Stadium.  ?b wgs84:lat ?lat. ?b wgs84:long ?long.
        </RestrictTo>
      </TargetDataset>     

 <LinkCondition>
 <Aggregate type="average" required="true">
  <Aggregate type="max" required="true" weight="2">
   <Compare metric="jaro" >
    <Input path="?a/rdfs:label" />
    <Input path="?b/rdfs:label" />
   </Compare>
  </Aggregate>
 <Compare metric="wgs84" required="true">
  <TransformInput function="concat">
   <Input path="?a/wgs84:lat" />
   <Input path="?a/wgs84:long" />
   <Param name="glue" value=" " />
  </TransformInput>
  <TransformInput function="concat">
   <Input path="?b/wgs84:lat" />
   <Input path="?b/wgs84:long" />
   <Param name="glue" value=" " />
  </TransformInput>
  <Param name="unit" value="km" />
  <Param name="threshold" value="4" />
  <Param name="curveStyle" value="logistic" />
 </Compare>
<!-- <Compare metric="num" weight="1">
  <Input path="?a/dbpedia-owl:populationTotal" />
  <Input path="?b/lgdo:population" />
 </Compare>-->
</Aggregate>
</LinkCondition>

      <Filter threshold="0.9" />

      <Outputs>
        <Output type="file" minConfidence="0.95">
          <Param name="file" value="1301310200652/stadium/links_accepted.nt" />
          <Param name="format" value="ntriples" />
        </Output>
        <Output type="file" maxConfidence="0.95">
          <Param name="file" value="1301310200652/stadium/links_verify.nt" />
          <Param name="format" value="ntriples" />
        </Output>
      </Outputs>
    </Interlink>
  </Interlinks>

</Silk>